pycalcids/__init__.py
pycalcids-0.0.1.dist-info/LICENSE.txt
pycalcids-0.0.1.dist-info/METADATA
pycalcids-0.0.1.dist-info/WHEEL
pycalcids-0.0.1.dist-info/top_level.txt
pycalcids-0.0.1.dist-info/RECORD
